LICENSE.txt
README.md
setup.cfg
setup.py
column_set/__init__.py
column_set/column_set.py
column_set.egg-info/PKG-INFO
column_set.egg-info/SOURCES.txt
column_set.egg-info/dependency_links.txt
column_set.egg-info/top_level.txt
tests/__init__.py
tests/test_column_set.py